colourmap/__init__.py
colourmap/colourmap.py
colourmap/examples.py
colourmap-1.2.0.dist-info/licenses/LICENSE
colourmap-1.2.0.dist-info/METADATA
colourmap-1.2.0.dist-info/WHEEL
colourmap-1.2.0.dist-info/top_level.txt
colourmap-1.2.0.dist-info/RECORD
