Metadata-Version: 2.4
Name: colourmap
Version: 1.2.0
Summary: Python package colourmap generates an N unique colors from the specified input colormap.
Author-email: Erdogan Taskesen <erdogant@gmail.com>
License: MIT License
Project-URL: Homepage, https://erdogant.github.io/colourmap
Project-URL: Download, https://github.com/erdogant/colourmap/archive/{version}.tar.gz
Keywords: Python,
Classifier: Programming Language :: Python :: 3
Classifier: License :: OSI Approved :: MIT License
Classifier: Operating System :: OS Independent
Requires-Python: >=3
License-File: LICENSE
Requires-Dist: matplotlib
Requires-Dist: numpy
Requires-Dist: scipy
Dynamic: license-file
